{"version":3,"kind":"Notebook","sha256":"f3abf8d056ec2b2244c730641226f9fef47de90195312123cfd2e4dd79729864","slug":"notebooks.timelapse-camera-tutorial","location":"/notebooks/timelapse-camera-tutorial.ipynb","dependencies":[],"frontmatter":{"title":"Time-lapse Cameras","content_includes_title":false,"kernelspec":{"name":"python3","display_name":"snow-cookbook-test","language":"python"},"authors":[{"nameParsed":{"literal":"The NASA Snow Observations Community","given":"The NASA Snow Observations","family":"Community"},"name":"The NASA Snow Observations Community","id":"contributors-myst-generated-uid-0"}],"open_access":true,"license":{"content":{"id":"CC-BY-4.0","url":"https://creativecommons.org/licenses/by/4.0/","name":"Creative Commons Attribution 4.0 International","free":true,"CC":true},"code":{"id":"Apache-2.0","url":"https://opensource.org/licenses/Apache-2.0","name":"Apache License 2.0","free":true,"osi":true}},"github":"https://github.com/SnowEx/snow-observations-cookbook","copyright":"2025","affiliations":[{"id":"UAlbany","name":"University at Albany (SUNY)","department":"Atmospheric and Environmental Sciences","url":"https://www.albany.edu/daes"},{"id":"CISL","name":"NSF National Center for Atmospheric Research","department":"Computational and Information Systems Lab","url":"https://www.cisl.ucar.edu"},{"id":"Unidata","name":"NSF Unidata","url":"https://www.unidata.ucar.edu"},{"id":"Argonne","name":"Argonne National Laboratory","department":"Environmental Science Division","url":"https://www.anl.gov/evs"},{"id":"CarbonPlan","name":"CarbonPlan","url":"https://carbonplan.org"},{"id":"NVIDIA","name":"NVIDIA Corporation","url":"https://www.nvidia.com/"}],"numbering":{"title":{"offset":1}},"source_url":"https://github.com/SnowEx/snow-observations-cookbook/blob/main/notebooks/timelapse-camera-tutorial.ipynb","edit_url":"https://github.com/SnowEx/snow-observations-cookbook/edit/main/notebooks/timelapse-camera-tutorial.ipynb","thumbnail":"/snow-observations-cookbook/build/timelapse-camera-tut-91bd3e2199e99c14dac6864ae3ff5a29.png","exports":[{"format":"ipynb","filename":"timelapse-camera-tutorial.ipynb","url":"/snow-observations-cookbook/build/timelapse-camera-tut-f27b97c789240029c3ee260516befd5d.ipynb"}]},"widgets":{},"mdast":{"type":"root","children":[{"type":"block","kind":"notebook-content","children":[{"type":"admonition","children":[{"type":"admonitionTitle","children":[{"type":"text","value":"Learning Objectives","position":{"start":{"line":3,"column":1},"end":{"line":3,"column":1}},"key":"fgi7I74Ed3"}],"key":"IF8EolpWVb"},{"type":"paragraph","position":{"start":{"line":5,"column":1},"end":{"line":5,"column":1}},"children":[{"type":"strong","position":{"start":{"line":5,"column":1},"end":{"line":5,"column":1}},"children":[{"type":"text","value":"At the conclusion of this tutorial, you will...:","position":{"start":{"line":5,"column":1},"end":{"line":5,"column":1}},"key":"htLq6VvoCR"}],"key":"JlDRpS6JBi"}],"key":"ADQGXV0kcL"},{"type":"list","ordered":false,"spread":false,"position":{"start":{"line":6,"column":1},"end":{"line":9,"column":1}},"children":[{"type":"listItem","spread":true,"position":{"start":{"line":6,"column":1},"end":{"line":6,"column":1}},"children":[{"type":"paragraph","children":[{"type":"text","value":"Know about all the time-lapse images available from the SnowEx 2017 and 2020 field campaigns","position":{"start":{"line":6,"column":1},"end":{"line":6,"column":1}},"key":"F7kTnifs36"}],"key":"rUMTe1jrzm"}],"key":"gJIifrZiuD"},{"type":"listItem","spread":true,"position":{"start":{"line":7,"column":1},"end":{"line":7,"column":1}},"children":[{"type":"paragraph","children":[{"type":"text","value":"View example time-lapse images from SnowEx 2020 and visualize their locations","position":{"start":{"line":7,"column":1},"end":{"line":7,"column":1}},"key":"hC1YzXsCSc"}],"key":"czQyZ7kfGg"}],"key":"cFLIwXp2CI"},{"type":"listItem","spread":true,"position":{"start":{"line":8,"column":1},"end":{"line":8,"column":1}},"children":[{"type":"paragraph","children":[{"type":"text","value":"Access snow depth measurements extracted from the SnowEx 2020 time-lapse images","position":{"start":{"line":8,"column":1},"end":{"line":8,"column":1}},"key":"c2bwTHkve8"}],"key":"YAc6SMiOT5"}],"key":"qewCSfR7c8"},{"type":"listItem","spread":true,"position":{"start":{"line":9,"column":1},"end":{"line":9,"column":1}},"children":[{"type":"paragraph","children":[{"type":"text","value":"Compare snow depths from different SnowEx 2020 time-lapse cameras","position":{"start":{"line":9,"column":1},"end":{"line":9,"column":1}},"key":"uV22LsMxvU"}],"key":"hcWkMTNYQb"}],"key":"ZUIIlD2QQ4"}],"key":"VhuEpFMe83"}],"key":"scSS6PkMAZ"}],"key":"Y8dvfAw2f8"},{"type":"block","kind":"notebook-content","children":[{"type":"heading","depth":2,"position":{"start":{"line":1,"column":1},"end":{"line":1,"column":1}},"children":[{"type":"text","value":"Time-lapse Cameras on Grand Mesa during SnowEx Field Campaigns","position":{"start":{"line":1,"column":1},"end":{"line":1,"column":1}},"key":"eH4Hc5eoiu"}],"identifier":"time-lapse-cameras-on-grand-mesa-during-snowex-field-campaigns","label":"Time-lapse Cameras on Grand Mesa during SnowEx Field Campaigns","html_id":"time-lapse-cameras-on-grand-mesa-during-snowex-field-campaigns","implicit":true,"key":"X5vyDu6xVu"},{"type":"paragraph","position":{"start":{"line":2,"column":1},"end":{"line":2,"column":1}},"children":[{"type":"text","value":"Time-lapse cameras were installed in both the SnowEx 2017 and 2020 field campaigns on Grand Mesa in similar locations.","position":{"start":{"line":2,"column":1},"end":{"line":2,"column":1}},"key":"CAk9N5zABu"}],"key":"IfopGVs0oD"},{"type":"paragraph","position":{"start":{"line":4,"column":1},"end":{"line":4,"column":1}},"children":[{"type":"strong","position":{"start":{"line":4,"column":1},"end":{"line":4,"column":1}},"children":[{"type":"text","value":"SnowEx 2017 Time-lapse Cameras","position":{"start":{"line":4,"column":1},"end":{"line":4,"column":1}},"key":"OUWbUnaM2v"}],"key":"vPQeYRrpeH"}],"key":"yVThH2cr36"},{"type":"list","ordered":false,"spread":false,"position":{"start":{"line":5,"column":1},"end":{"line":10,"column":1}},"children":[{"type":"listItem","spread":true,"position":{"start":{"line":5,"column":1},"end":{"line":5,"column":1}},"children":[{"type":"paragraph","children":[{"type":"text","value":"28 Total Time-lapse Cameras","position":{"start":{"line":5,"column":1},"end":{"line":5,"column":1}},"key":"Z4LDlI0wLX"}],"key":"YFudu5InIQ"}],"key":"pcdadVtX4s"},{"type":"listItem","spread":true,"position":{"start":{"line":6,"column":1},"end":{"line":6,"column":1}},"children":[{"type":"paragraph","children":[{"type":"text","value":"Capturing the entire winter season (September 2016-June 2017)","position":{"start":{"line":6,"column":1},"end":{"line":6,"column":1}},"key":"p7YdYXkGPc"}],"key":"eP77NYni8B"}],"key":"APaBBwcbDb"},{"type":"listItem","spread":true,"position":{"start":{"line":7,"column":1},"end":{"line":7,"column":1}},"children":[{"type":"paragraph","children":[{"type":"text","value":"Taking 4 photos/day at 8AM, 10AM, 12PM, 2PM, 4PM","position":{"start":{"line":7,"column":1},"end":{"line":7,"column":1}},"key":"oLUAiQUcJ5"}],"key":"Duvy6e6GtP"}],"key":"e2Wmkvi075"},{"type":"listItem","spread":true,"position":{"start":{"line":8,"column":1},"end":{"line":8,"column":1}},"children":[{"type":"paragraph","children":[{"type":"text","value":"An orange pole was installed in front of 15 cameras for snow depth measurements","position":{"start":{"line":8,"column":1},"end":{"line":8,"column":1}},"key":"nAvgNdereC"}],"key":"Ncp5mDkEnD"}],"key":"cJg2cZvy7Q"},{"type":"listItem","spread":true,"position":{"start":{"line":9,"column":1},"end":{"line":10,"column":1}},"children":[{"type":"paragraph","children":[{"type":"text","value":"Time-lapse images have been submitted to the NSIDC by Mark Raleigh with all the required metadata (e.g., locations, naming convention, etc.) for use.","position":{"start":{"line":9,"column":1},"end":{"line":9,"column":1}},"key":"NHUEBoUtnD"}],"key":"HUJlAsq5qe"}],"key":"mbycvi2HzX"}],"key":"NpHEijtgPA"},{"type":"paragraph","position":{"start":{"line":11,"column":1},"end":{"line":11,"column":1}},"children":[{"type":"strong","position":{"start":{"line":11,"column":1},"end":{"line":11,"column":1}},"children":[{"type":"text","value":"SnowEx 2020 Time-lapse Cameras","position":{"start":{"line":11,"column":1},"end":{"line":11,"column":1}},"key":"rq6SuJFJV9"}],"key":"Tmj1omuKHp"}],"key":"kMizD45TS5"},{"type":"list","ordered":false,"spread":false,"position":{"start":{"line":12,"column":1},"end":{"line":19,"column":1}},"children":[{"type":"listItem","spread":true,"position":{"start":{"line":12,"column":1},"end":{"line":12,"column":1}},"children":[{"type":"paragraph","children":[{"type":"text","value":"29 Total Time-lapse Cameras","position":{"start":{"line":12,"column":1},"end":{"line":12,"column":1}},"key":"iiwG5dOCvq"}],"key":"o3bJtDKP1P"}],"key":"hSKW1Wr8BH"},{"type":"listItem","spread":true,"position":{"start":{"line":13,"column":1},"end":{"line":13,"column":1}},"children":[{"type":"paragraph","children":[{"type":"text","value":"Capturing the entire winter season (September 2019-June 2020)","position":{"start":{"line":13,"column":1},"end":{"line":13,"column":1}},"key":"h6pGIvlPcs"}],"key":"dp3jLXTXSt"}],"key":"e5KS49dKgI"},{"type":"listItem","spread":true,"position":{"start":{"line":14,"column":1},"end":{"line":14,"column":1}},"children":[{"type":"paragraph","children":[{"type":"text","value":"Taking 3 photos/day at 11AM, 12PM, 1PM or 2 photos/day at 11AM and 12PM","position":{"start":{"line":14,"column":1},"end":{"line":14,"column":1}},"key":"Vns0X71d0A"}],"key":"ObQEEMrdym"}],"key":"O8Nb10SsUh"},{"type":"listItem","spread":true,"position":{"start":{"line":15,"column":1},"end":{"line":15,"column":1}},"children":[{"type":"paragraph","children":[{"type":"text","value":"A red pole was installed in front of each camera for snow depth measurements.","position":{"start":{"line":15,"column":1},"end":{"line":15,"column":1}},"key":"T186mi13HI"}],"key":"QC5l2QdPvQ"}],"key":"zcnCTGXPFZ"},{"type":"listItem","spread":true,"position":{"start":{"line":16,"column":1},"end":{"line":19,"column":1}},"children":[{"type":"paragraph","children":[{"type":"text","value":"Cameras were installed on the east and west side of the Grand Mesa, across a vegetation scale of 1-9, using the convention ","position":{"start":{"line":16,"column":1},"end":{"line":16,"column":1}},"key":"E5WCQjnHhx"},{"type":"strong","position":{"start":{"line":16,"column":1},"end":{"line":16,"column":1}},"children":[{"type":"text","value":"XMR","position":{"start":{"line":16,"column":1},"end":{"line":16,"column":1}},"key":"uPcWQjzJlo"}],"key":"d519wzFWe7"},{"type":"text","value":":","position":{"start":{"line":16,"column":1},"end":{"line":16,"column":1}},"key":"MRMfy9hIb8"}],"key":"ADqv4KioJ2"},{"type":"list","ordered":false,"spread":false,"position":{"start":{"line":17,"column":1},"end":{"line":19,"column":1}},"children":[{"type":"listItem","spread":true,"position":{"start":{"line":17,"column":1},"end":{"line":17,"column":1}},"children":[{"type":"paragraph","children":[{"type":"strong","position":{"start":{"line":17,"column":1},"end":{"line":17,"column":1}},"children":[{"type":"text","value":"X","position":{"start":{"line":17,"column":1},"end":{"line":17,"column":1}},"key":"a0z8ue9rOR"}],"key":"isi0p5t8qs"},{"type":"text","value":" = East (E) or West (W) areas of the Mesa","position":{"start":{"line":17,"column":1},"end":{"line":17,"column":1}},"key":"TkwBUsqIw1"}],"key":"Fq96XRTUYd"}],"key":"RP3HyONzuk"},{"type":"listItem","spread":true,"position":{"start":{"line":18,"column":1},"end":{"line":18,"column":1}},"children":[{"type":"paragraph","children":[{"type":"strong","position":{"start":{"line":18,"column":1},"end":{"line":18,"column":1}},"children":[{"type":"text","value":"M","position":{"start":{"line":18,"column":1},"end":{"line":18,"column":1}},"key":"IBD0kXYp0n"}],"key":"PxRhVV5uxP"},{"type":"text","value":" = number 1-9, representing 1 (least vegetation) to 9 (most vegetation). Within each vegetation class, there were three sub-classes of snow depths derived from 2017 SnowEx lidar measurements.","position":{"start":{"line":18,"column":1},"end":{"line":18,"column":1}},"key":"J6Np4Fe0P3"}],"key":"JqSv9EAF1i"}],"key":"VqOrLpzAyS"},{"type":"listItem","spread":true,"position":{"start":{"line":19,"column":1},"end":{"line":19,"column":1}},"children":[{"type":"paragraph","children":[{"type":"strong","position":{"start":{"line":19,"column":1},"end":{"line":19,"column":1}},"children":[{"type":"text","value":"R","position":{"start":{"line":19,"column":1},"end":{"line":19,"column":1}},"key":"Lomu6MgiZI"}],"key":"ORS12HGVV7"},{"type":"text","value":" = Replicate of vegetation assignment, either A, B, C, D, or E.","position":{"start":{"line":19,"column":1},"end":{"line":19,"column":1}},"key":"ochVeuIASx"}],"key":"RiscEF2txL"}],"key":"CnnUMUh5Bp"}],"key":"SK9tTJ5pai"}],"key":"DEQdD6thr1"}],"key":"K9Ut1ONxJb"}],"key":"zV6SzERcko"},{"type":"block","kind":"notebook-content","children":[{"type":"heading","depth":3,"position":{"start":{"line":1,"column":1},"end":{"line":1,"column":1}},"children":[{"type":"text","value":"An automated way of viewing and mapping time-lapse photos","position":{"start":{"line":1,"column":1},"end":{"line":1,"column":1}},"key":"K0qaf5qjzU"}],"identifier":"an-automated-way-of-viewing-and-mapping-time-lapse-photos","label":"An automated way of viewing and mapping time-lapse photos","html_id":"an-automated-way-of-viewing-and-mapping-time-lapse-photos","implicit":true,"key":"ufu3NgJYOt"}],"key":"toHCJmfEqw"},{"type":"block","kind":"notebook-content","children":[{"type":"paragraph","position":{"start":{"line":1,"column":1},"end":{"line":1,"column":1}},"children":[{"type":"text","value":"First, we will procedurally import the necessary packages to access the data. To access the snow depths at each camera station, we will use the SnowEx database (","position":{"start":{"line":1,"column":1},"end":{"line":1,"column":1}},"key":"cWfGkLm5uW"},{"type":"inlineCode","value":"snowexsql","position":{"start":{"line":1,"column":1},"end":{"line":1,"column":1}},"key":"g6MSLHy120"},{"type":"text","value":") to access the depths as ","position":{"start":{"line":1,"column":1},"end":{"line":1,"column":1}},"key":"fYbnwCZDon"},{"type":"inlineCode","value":"PointMeasurements","position":{"start":{"line":1,"column":1},"end":{"line":1,"column":1}},"key":"WnrfhcnEiM"},{"type":"text","value":".","position":{"start":{"line":1,"column":1},"end":{"line":1,"column":1}},"key":"sPkCLaDnUe"}],"key":"RarIHjEnkD"}],"key":"LRvwSfZ2lx"},{"type":"block","kind":"notebook-code","children":[{"type":"code","lang":"python","executable":true,"value":"from snowexsql.api import PointMeasurements\n\n# Import information for all point measurement types\nmeasurements = PointMeasurements()\n\n# List unique instruments\nresults = measurements.all_instruments\nprint('\\nAvailable Instruments = {}'.format(', '.join([str(r) for r in results])))","key":"sCWZpEAJHr"},{"type":"outputs","id":"Is59H36HleMMyoZEMgrSw","children":[{"type":"output","children":[],"jupyter_data":{"output_type":"stream","name":"stdout","text":"\nAvailable Instruments = mesa, magnaprobe, camera, pulseEkko pro 1 GHz GPR, None, Mala 1600 MHz GPR, Mala 800 MHz GPR, pulse EKKO Pro multi-polarization 1 GHz GPR, pit ruler\n"},"key":"pTAsbTSGFg"}],"key":"liKFyH4iUA"}],"key":"fMo19Fy8uR"},{"type":"block","kind":"notebook-code","children":[{"type":"code","lang":"python","executable":true,"value":"# Packages for data analysis \nimport geopandas as gpd # geopandas library for data analysis and visualization\nimport pandas as pd # pandas as to read csv data and visualize tabular data\nimport numpy as np # numpy for data analysis \n\n# Packages for data visualization\nimport matplotlib as mpl\nimport matplotlib.pyplot as plt # matplotlib.pyplot for plotting images and graphs\n\nplt.rcParams['figure.figsize']  = (10, 4) # figure size\nplt.rcParams['axes.titlesize']  = 14 # title size \nplt.rcParams['axes.labelsize']  = 12 # axes label size \nplt.rcParams['xtick.labelsize'] = 11 # x tick label size \nplt.rcParams['ytick.labelsize'] = 11 # y tick label size \nplt.rcParams['legend.fontsize'] = 11 # legend size \nmpl.rcParams['figure.dpi'] = 100","key":"SrSYoKiPWa"},{"type":"outputs","id":"4xS8FtQpTfPMpShcDkypw","children":[],"key":"t4B4KSY4dV"}],"key":"cCGNOkKnEa"},{"type":"block","kind":"notebook-code","children":[{"type":"code","lang":"python","executable":true,"value":"# Query the database for camera-based snow depths\ncamera_depths = measurements.from_filter(\n    type=\"depth\",\n    site_name=\"Grand Mesa\",\n    instrument=\"camera\",\n    limit = 13371\n)\n\ncamera_depths.head()","key":"VLV0cJE24T"},{"type":"outputs","id":"ndGqZYU5ValuWYyAG9H0z","children":[{"type":"output","children":[],"jupyter_data":{"output_type":"execute_result","execution_count":3,"metadata":{},"data":{"text/plain":{"content":"  version_number        equipment     value   latitude   longitude  \\\n0           None  camera id = E9C  62.39355  39.098962 -107.893702   \n1           None  camera id = E9C  61.48947  39.098962 -107.893702   \n2           None  camera id = E9C  60.58539  39.098962 -107.893702   \n3           None  camera id = E9C  59.68131  39.098962 -107.893702   \n4           None  camera id = E9C  57.87315  39.098962 -107.893702   \n\n       northing        easting elevation  utm_zone  \\\n0  4.331746e+06  249756.705396      None        13   \n1  4.331746e+06  249756.705396      None        13   \n2  4.331746e+06  249756.705396      None        13   \n3  4.331746e+06  249756.705396      None        13   \n4  4.331746e+06  249756.705396      None        13   \n\n                             geom  ...        date  \\\n0  POINT (249756.705 4331745.771)  ...  2020-05-06   \n1  POINT (249756.705 4331745.771)  ...  2020-05-06   \n2  POINT (249756.705 4331745.771)  ...  2020-05-07   \n3  POINT (249756.705 4331745.771)  ...  2020-05-07   \n4  POINT (249756.705 4331745.771)  ...  2020-05-07   \n\n                      time_created time_updated     id   doi date_accessed  \\\n0 2022-06-30 22:58:59.800562+00:00         None  44558  None    2022-06-30   \n1 2022-06-30 22:58:59.800562+00:00         None  44559  None    2022-06-30   \n2 2022-06-30 22:58:59.800562+00:00         None  44560  None    2022-06-30   \n3 2022-06-30 22:58:59.800562+00:00         None  44561  None    2022-06-30   \n4 2022-06-30 22:58:59.800562+00:00         None  44562  None    2022-06-30   \n\n   instrument   type units                         observers  \n0      camera  depth    cm  Catherine Breen, Cassie Lumbrazo  \n1      camera  depth    cm  Catherine Breen, Cassie Lumbrazo  \n2      camera  depth    cm  Catherine Breen, Cassie Lumbrazo  \n3      camera  depth    cm  Catherine Breen, Cassie Lumbrazo  \n4      camera  depth    cm  Catherine Breen, Cassie Lumbrazo  \n\n[5 rows x 23 columns]","content_type":"text/plain"},"text/html":{"content":"<div>\n<style scoped>\n    .dataframe tbody tr th:only-of-type {\n        vertical-align: middle;\n    }\n\n    .dataframe tbody tr th {\n        vertical-align: top;\n    }\n\n    .dataframe thead th {\n        text-align: right;\n    }\n</style>\n<table border=\"1\" class=\"dataframe\">\n  <thead>\n    <tr style=\"text-align: right;\">\n      <th></th>\n      <th>version_number</th>\n      <th>equipment</th>\n      <th>value</th>\n      <th>latitude</th>\n      <th>longitude</th>\n      <th>northing</th>\n      <th>easting</th>\n      <th>elevation</th>\n      <th>utm_zone</th>\n      <th>geom</th>\n      <th>...</th>\n      <th>date</th>\n      <th>time_created</th>\n      <th>time_updated</th>\n      <th>id</th>\n      <th>doi</th>\n      <th>date_accessed</th>\n      <th>instrument</th>\n      <th>type</th>\n      <th>units</th>\n      <th>observers</th>\n    </tr>\n  </thead>\n  <tbody>\n    <tr>\n      <th>0</th>\n      <td>None</td>\n      <td>camera id = E9C</td>\n      <td>62.39355</td>\n      <td>39.098962</td>\n      <td>-107.893702</td>\n      <td>4.331746e+06</td>\n      <td>249756.705396</td>\n      <td>None</td>\n      <td>13</td>\n      <td>POINT (249756.705 4331745.771)</td>\n      <td>...</td>\n      <td>2020-05-06</td>\n      <td>2022-06-30 22:58:59.800562+00:00</td>\n      <td>None</td>\n      <td>44558</td>\n      <td>None</td>\n      <td>2022-06-30</td>\n      <td>camera</td>\n      <td>depth</td>\n      <td>cm</td>\n      <td>Catherine Breen, Cassie Lumbrazo</td>\n    </tr>\n    <tr>\n      <th>1</th>\n      <td>None</td>\n      <td>camera id = E9C</td>\n      <td>61.48947</td>\n      <td>39.098962</td>\n      <td>-107.893702</td>\n      <td>4.331746e+06</td>\n      <td>249756.705396</td>\n      <td>None</td>\n      <td>13</td>\n      <td>POINT (249756.705 4331745.771)</td>\n      <td>...</td>\n      <td>2020-05-06</td>\n      <td>2022-06-30 22:58:59.800562+00:00</td>\n      <td>None</td>\n      <td>44559</td>\n      <td>None</td>\n      <td>2022-06-30</td>\n      <td>camera</td>\n      <td>depth</td>\n      <td>cm</td>\n      <td>Catherine Breen, Cassie Lumbrazo</td>\n    </tr>\n    <tr>\n      <th>2</th>\n      <td>None</td>\n      <td>camera id = E9C</td>\n      <td>60.58539</td>\n      <td>39.098962</td>\n      <td>-107.893702</td>\n      <td>4.331746e+06</td>\n      <td>249756.705396</td>\n      <td>None</td>\n      <td>13</td>\n      <td>POINT (249756.705 4331745.771)</td>\n      <td>...</td>\n      <td>2020-05-07</td>\n      <td>2022-06-30 22:58:59.800562+00:00</td>\n      <td>None</td>\n      <td>44560</td>\n      <td>None</td>\n      <td>2022-06-30</td>\n      <td>camera</td>\n      <td>depth</td>\n      <td>cm</td>\n      <td>Catherine Breen, Cassie Lumbrazo</td>\n    </tr>\n    <tr>\n      <th>3</th>\n      <td>None</td>\n      <td>camera id = E9C</td>\n      <td>59.68131</td>\n      <td>39.098962</td>\n      <td>-107.893702</td>\n      <td>4.331746e+06</td>\n      <td>249756.705396</td>\n      <td>None</td>\n      <td>13</td>\n      <td>POINT (249756.705 4331745.771)</td>\n      <td>...</td>\n      <td>2020-05-07</td>\n      <td>2022-06-30 22:58:59.800562+00:00</td>\n      <td>None</td>\n      <td>44561</td>\n      <td>None</td>\n      <td>2022-06-30</td>\n      <td>camera</td>\n      <td>depth</td>\n      <td>cm</td>\n      <td>Catherine Breen, Cassie Lumbrazo</td>\n    </tr>\n    <tr>\n      <th>4</th>\n      <td>None</td>\n      <td>camera id = E9C</td>\n      <td>57.87315</td>\n      <td>39.098962</td>\n      <td>-107.893702</td>\n      <td>4.331746e+06</td>\n      <td>249756.705396</td>\n      <td>None</td>\n      <td>13</td>\n      <td>POINT (249756.705 4331745.771)</td>\n      <td>...</td>\n      <td>2020-05-07</td>\n      <td>2022-06-30 22:58:59.800562+00:00</td>\n      <td>None</td>\n      <td>44562</td>\n      <td>None</td>\n      <td>2022-06-30</td>\n      <td>camera</td>\n      <td>depth</td>\n      <td>cm</td>\n      <td>Catherine Breen, Cassie Lumbrazo</td>\n    </tr>\n  </tbody>\n</table>\n<p>5 rows × 23 columns</p>\n</div>","content_type":"text/html"}}},"key":"H04Ktt4bu4"}],"key":"GPx6Hzl0uy"}],"key":"oj4z7DBAFu"},{"type":"block","kind":"notebook-content","children":[{"type":"heading","depth":4,"position":{"start":{"line":1,"column":1},"end":{"line":1,"column":1}},"children":[{"type":"text","value":"Plot the camera locations, using snow pit locations for reference.","position":{"start":{"line":1,"column":1},"end":{"line":1,"column":1}},"key":"B7VUyRVM8F"}],"identifier":"plot-the-camera-locations-using-snow-pit-locations-for-reference","label":"Plot the camera locations, using snow pit locations for reference.","html_id":"plot-the-camera-locations-using-snow-pit-locations-for-reference","implicit":true,"key":"M5xNrV216Z"}],"key":"kocBlKiS2Z"},{"type":"block","kind":"notebook-code","children":[{"type":"code","lang":"python","executable":true,"value":"camera_depths.explore(tooltip=['equipment','date','latitude','longitude','value','type','units'])","key":"RKCQpUoQP7"},{"type":"outputs","id":"FSQCjoA9bVpPfokRTHoiw","children":[{"type":"output","children":[],"jupyter_data":{"output_type":"execute_result","execution_count":4,"metadata":{},"data":{"text/plain":{"content":"<folium.folium.Map at 0x7f7d15db97f0>","content_type":"text/plain"},"text/html":{"content_type":"text/html","hash":"aa573d1959e7594185cc79d9c6274993","path":"/snow-observations-cookbook/build/aa573d1959e7594185cc79d9c6274993.html"}}},"key":"wspu1mQJHA"}],"key":"EEINNZhJ5P"}],"key":"WUonXJAgJN"},{"type":"block","kind":"notebook-content","children":[{"type":"heading","depth":2,"position":{"start":{"line":1,"column":1},"end":{"line":1,"column":1}},"children":[{"type":"text","value":"Viewing the time-lapse photos","position":{"start":{"line":1,"column":1},"end":{"line":1,"column":1}},"key":"gGzBcNikZS"}],"identifier":"viewing-the-time-lapse-photos","label":"Viewing the time-lapse photos","html_id":"viewing-the-time-lapse-photos","implicit":true,"key":"KWLkYNIru4"},{"type":"paragraph","position":{"start":{"line":2,"column":1},"end":{"line":2,"column":1}},"children":[{"type":"text","value":"Thanks to the SnowEx database, we were able to easily access snow depths at each site. However, if we wish to examine the camera imagery, we will need to be a bit more creative.","position":{"start":{"line":2,"column":1},"end":{"line":2,"column":1}},"key":"w1bKBKv3WS"}],"key":"CX25ZGPEe7"},{"type":"paragraph","position":{"start":{"line":4,"column":1},"end":{"line":4,"column":1}},"children":[{"type":"text","value":"The images are available through NSIDC, so we will use ","position":{"start":{"line":4,"column":1},"end":{"line":4,"column":1}},"key":"WtlcRQTqhC"},{"type":"inlineCode","value":"earthaccess","position":{"start":{"line":4,"column":1},"end":{"line":4,"column":1}},"key":"iDkypBVhs1"},{"type":"text","value":" to grab one of the image archives.","position":{"start":{"line":4,"column":1},"end":{"line":4,"column":1}},"key":"xeIAx8Ir7Y"}],"key":"megVPN8BFA"}],"key":"CYijvL2t9j"},{"type":"block","kind":"notebook-content","children":[{"type":"admonition","kind":"note","children":[{"type":"admonitionTitle","children":[{"type":"text","value":"Earthdata Login Authentication","position":{"start":{"line":1,"column":1},"end":{"line":1,"column":1}},"key":"qUNgSbfg3w"}],"key":"NIMaZ8ev0u"},{"type":"paragraph","position":{"start":{"line":3,"column":1},"end":{"line":3,"column":1}},"children":[{"type":"text","value":"This tutorial requires NASA Earthdata Login credentials to access NSIDC data.","position":{"start":{"line":3,"column":1},"end":{"line":3,"column":1}},"key":"gW8FOmhxQM"}],"key":"JLLR2ODvc0"},{"type":"paragraph","position":{"start":{"line":5,"column":1},"end":{"line":5,"column":1}},"children":[{"type":"link","url":"https://urs.earthdata.nasa.gov/","position":{"start":{"line":5,"column":1},"end":{"line":5,"column":1}},"children":[{"type":"text","value":"Register for free","position":{"start":{"line":5,"column":1},"end":{"line":5,"column":1}},"key":"bPIdfkdK9d"}],"urlSource":"https://urs.earthdata.nasa.gov/","key":"duOJ22VsPd"},{"type":"text","value":" if you don’t have an account","position":{"start":{"line":5,"column":1},"end":{"line":5,"column":1}},"key":"PFVxMzsglB"}],"key":"xWMbWrTUGv"},{"type":"paragraph","position":{"start":{"line":7,"column":1},"end":{"line":9,"column":1}},"children":[{"type":"text","value":"Once you have a username and password, you can either enter these in manually\nin the ","position":{"start":{"line":7,"column":1},"end":{"line":7,"column":1}},"key":"CvpnY9EE4D"},{"type":"inlineCode","value":"strategy=\"interactive\"","position":{"start":{"line":7,"column":1},"end":{"line":7,"column":1}},"key":"iCEjs6hBvn"},{"type":"text","value":" mode (as coded below), or you can configure your\nlocal envrionment as follows:","position":{"start":{"line":7,"column":1},"end":{"line":7,"column":1}},"key":"qodLmCdYW6"}],"key":"e4DDqSHX6d"},{"type":"paragraph","position":{"start":{"line":11,"column":1},"end":{"line":11,"column":1}},"children":[{"type":"strong","position":{"start":{"line":11,"column":1},"end":{"line":11,"column":1}},"children":[{"type":"text","value":"Here’s how to configure your local system for this to work:","position":{"start":{"line":11,"column":1},"end":{"line":11,"column":1}},"key":"TB87ZRYBbR"}],"key":"vhOW8ijjLX"}],"key":"XVu9dBXMX7"},{"type":"list","ordered":false,"spread":false,"position":{"start":{"line":12,"column":1},"end":{"line":14,"column":1}},"children":[{"type":"listItem","spread":true,"position":{"start":{"line":12,"column":1},"end":{"line":12,"column":1}},"children":[{"type":"paragraph","children":[{"type":"text","value":"First time: Run ","position":{"start":{"line":12,"column":1},"end":{"line":12,"column":1}},"key":"OOLjKYMGGG"},{"type":"inlineCode","value":"earthaccess.login()","position":{"start":{"line":12,"column":1},"end":{"line":12,"column":1}},"key":"Z26suv6ERQ"},{"type":"text","value":" without the strategy parameter to authenticate interactively","position":{"start":{"line":12,"column":1},"end":{"line":12,"column":1}},"key":"b5TkT0Y1r5"}],"key":"stsfwtpHvj"}],"key":"RESWBpagy7"},{"type":"listItem","spread":true,"position":{"start":{"line":13,"column":1},"end":{"line":14,"column":1}},"children":[{"type":"paragraph","children":[{"type":"text","value":"This creates a ","position":{"start":{"line":13,"column":1},"end":{"line":13,"column":1}},"key":"BHs7Y5il2G"},{"type":"inlineCode","value":".netrc","position":{"start":{"line":13,"column":1},"end":{"line":13,"column":1}},"key":"mcIMcJMG3c"},{"type":"text","value":" file for future sessions","position":{"start":{"line":13,"column":1},"end":{"line":13,"column":1}},"key":"Ne5NpsT5ME"}],"key":"uAGVbGJYgT"}],"key":"AcofeC3dsl"}],"key":"jbQEVs8vm2"},{"type":"paragraph","position":{"start":{"line":15,"column":1},"end":{"line":15,"column":1}},"children":[{"type":"text","value":"After making those changes, you should switch to ","position":{"start":{"line":15,"column":1},"end":{"line":15,"column":1}},"key":"oLiUZTUL4F"},{"type":"inlineCode","value":"strategy=\"environment\"","position":{"start":{"line":15,"column":1},"end":{"line":15,"column":1}},"key":"tednIjKmhm"},{"type":"text","value":" below!","position":{"start":{"line":15,"column":1},"end":{"line":15,"column":1}},"key":"X0JQmNTqt2"}],"key":"fnfJqHvXYa"}],"key":"WCTU8lrDaf"}],"key":"euEwN4ymIi"},{"type":"block","kind":"notebook-code","children":[{"type":"code","lang":"python","executable":true,"value":"import earthaccess\n\n# Authenticate with Earthdata Login servers\ntry:\n    auth = earthaccess.login(strategy=\"environment\")\n    print(\"✓ Successfully authenticated with Earthdata Login\")\n# Search for camera imagery (only if authenticated)\n    granules = earthaccess.search_data(\n        doi = \"10.5067/WYRNU50R9L5R\"\n    )\n    print(granules[0].data_links())\nexcept Exception as e:\n    print(f\"⚠ Authentication failed: {e}\")\n    print(\"This is expected in automated builds. \\\n           Interactive users should run earthaccess.login() to authenticate.\")\n    granules = None","key":"yAL8oJYSy7"},{"type":"outputs","id":"yP9dXykS9Zq2HrCqI36aZ","children":[{"type":"output","children":[],"jupyter_data":{"output_type":"stream","name":"stdout","text":"⚠ Authentication failed: Either the environment variables EARTHDATA_USERNAME and EARTHDATA_PASSWORD must both be set, or EARTHDATA_TOKEN must be set for the 'environment' login strategy.\nThis is expected in automated builds.            Interactive users should run earthaccess.login() to authenticate.\n"},"key":"Nl8HRe3Ky0"},{"type":"output","children":[],"jupyter_data":{"output_type":"stream","name":"stderr","text":"/home/runner/micromamba/envs/snow-observations-cookbook-test/lib/python3.14/site-packages/tqdm/auto.py:21: TqdmWarning: IProgress not found. Please update jupyter and ipywidgets. See https://ipywidgets.readthedocs.io/en/stable/user_install.html\n  from .autonotebook import tqdm as notebook_tqdm\n"},"key":"CvbbsGuWh8"}],"key":"tA56dplNcw"}],"key":"vAmSALrAJT"},{"type":"block","kind":"notebook-code","children":[{"type":"code","lang":"python","executable":true,"value":"# Load the files into memory (only if authenticated)\nif granules:\n    files = earthaccess.open(granules)\nelse:\n    print(\"⚠ Skipping remote data access - using local sample data instead\")\n    files = None","key":"YN205vLlVk"},{"type":"outputs","id":"ZIl7eFmnjPaN8OqXbOjXZ","children":[{"type":"output","children":[],"jupyter_data":{"output_type":"stream","name":"stdout","text":"⚠ Skipping remote data access - using local sample data instead\n"},"key":"pK2MU5eGnL"}],"key":"XMerEY66Ql"}],"key":"IXQ3gNR937"},{"type":"block","kind":"notebook-content","children":[{"type":"admonition","kind":"warning","children":[{"type":"admonitionTitle","children":[{"type":"text","value":"Large Downloads Ahead!","position":{"start":{"line":1,"column":1},"end":{"line":1,"column":1}},"key":"IKZvHQg6RM"}],"key":"qTsCCgypXd"},{"type":"paragraph","position":{"start":{"line":3,"column":1},"end":{"line":3,"column":1}},"children":[{"type":"text","value":"Looking at the above data links, one will notice that the images are saved in ","position":{"start":{"line":3,"column":1},"end":{"line":3,"column":1}},"key":"f45OAnspZO"},{"type":"inlineCode","value":".tar.gz","position":{"start":{"line":3,"column":1},"end":{"line":3,"column":1}},"key":"osuX8F8moO"},{"type":"text","value":" format. We can read files through ","position":{"start":{"line":3,"column":1},"end":{"line":3,"column":1}},"key":"jVDrHPbvay"},{"type":"inlineCode","value":"earthaccess","position":{"start":{"line":3,"column":1},"end":{"line":3,"column":1}},"key":"m3S8ItMrSx"},{"type":"text","value":" in this format, but it will require some more work than simply downloading the data.","position":{"start":{"line":3,"column":1},"end":{"line":3,"column":1}},"key":"cicjmy3Dhc"}],"key":"nlkOEQRxvc"},{"type":"paragraph","position":{"start":{"line":5,"column":1},"end":{"line":5,"column":1}},"children":[{"type":"text","value":"Users may download the files if they wish, but they are on the larger side (900+ Mb). If you wish to avoid large data downloads, then the below code will help with the process. However, be aware that the code can be rather memory intensive. If running this code on CryoCloud, then consider using larger memory allocations (4+ Gb).","position":{"start":{"line":5,"column":1},"end":{"line":5,"column":1}},"key":"K7GwIINEDT"}],"key":"rqZMKL7JNY"}],"key":"f1uvtBP6S7"},{"type":"paragraph","position":{"start":{"line":9,"column":1},"end":{"line":9,"column":1}},"children":[{"type":"text","value":"Here is how you would read in every file in the large ","position":{"start":{"line":9,"column":1},"end":{"line":9,"column":1}},"key":"LjNYAUPqVO"},{"type":"inlineCode","value":"tar.gz","position":{"start":{"line":9,"column":1},"end":{"line":9,"column":1}},"key":"zPEgqnaFee"},{"type":"text","value":" from earthaccess into memory:","position":{"start":{"line":9,"column":1},"end":{"line":9,"column":1}},"key":"v2dbXwgsy7"}],"key":"PJwH9FFwCQ"},{"type":"paragraph","position":{"start":{"line":11,"column":1},"end":{"line":11,"column":1}},"children":[{"type":"inlineCode","value":"file_content = files[0].read()","position":{"start":{"line":11,"column":1},"end":{"line":11,"column":1}},"key":"jnUjERDjFU"}],"key":"Wg0yzGrSJ6"}],"key":"c1tNKANyoF"},{"type":"block","kind":"notebook-content","children":[{"type":"admonition","kind":"tip","children":[{"type":"admonitionTitle","children":[{"type":"text","value":"Simplifying the download for learning purposes","position":{"start":{"line":1,"column":1},"end":{"line":1,"column":1}},"key":"cID5OIb9gU"}],"key":"FO2kxO7Jdg"},{"type":"paragraph","position":{"start":{"line":3,"column":1},"end":{"line":3,"column":1}},"children":[{"type":"text","value":"For the sake of this tutorial we will create a synthetic tar.gz file with just three images we want to show here.","position":{"start":{"line":3,"column":1},"end":{"line":3,"column":1}},"key":"FXRQuAtlc8"}],"key":"gu3oGMOJx6"}],"key":"VqQJF3N7Vc"}],"key":"md1c7U5wO5"},{"type":"block","kind":"notebook-code","children":[{"type":"code","lang":"python","executable":true,"value":"file_content = 'data/sample-data.tar.gz'\n","key":"dgt1ClCygi"},{"type":"outputs","id":"0A6B5sbvntt7itRSLkvMM","children":[],"key":"XrKPz99W5i"}],"key":"hzVL3oUcIK"},{"type":"block","kind":"notebook-code","children":[{"type":"code","lang":"python","executable":true,"value":"import tarfile\nfrom io import BytesIO\nfrom datetime import datetime\nfrom PIL import Image\nimport matplotlib.pyplot as plt\n\njpg_files = []\n# Open the tarfile remotely\nwith tarfile.open(file_content, mode=\"r:gz\") as tar:\n    # Identify contents of tarfile\n    members = tar.getmembers()\n\n    # Loop through tarfile contents for images of interest\n    fig, ax = plt.subplots(1,3, figsize=(12,12))\n    ax.flatten()\n    for member in members:\n        if member.name.lower().endswith('.jpg'):\n            jpg_file = tar.extractfile(member).read()\n            \n            # Estimate datetime from image\n            creationTime = member.mtime\n            dt_c = datetime.fromtimestamp(creationTime)\n            formatted_datetime = dt_c.strftime(\"%m/%d/%Y %H:%M\")\n\n            desired_datetimes = ['09/27/2016 15:13',\n                                 '11/08/2016 14:00',\n                                 '12/10/2016 14:00']\n            \n            # Append files with desired datetime\n            for idx,dt in enumerate(desired_datetimes):\n                if formatted_datetime == dt:\n                    image = Image.open(BytesIO(jpg_file))\n                    ax[idx].imshow(image)\n                    ax[idx].set_title(desired_datetimes[idx])\n                    ax[idx].axis('off')\n\n    plt.tight_layout()","key":"JyCvQxOAVM"},{"type":"outputs","id":"fWEdwhmKJhmViczyDztDA","children":[{"type":"output","children":[],"jupyter_data":{"output_type":"display_data","metadata":{},"data":{"text/plain":{"content":"<Figure size 1200x1200 with 3 Axes>","content_type":"text/plain"},"image/png":{"content_type":"image/png","hash":"d9d703c760b2c641c2411c8a1386d4fe","path":"/snow-observations-cookbook/build/d9d703c760b2c641c2411c8a1386d4fe.png"}}},"key":"fgclPYMcyI"}],"key":"udLojT7cNU"}],"key":"wXicnRBiNh"},{"type":"block","kind":"notebook-content","children":[{"type":"heading","depth":2,"position":{"start":{"line":1,"column":1},"end":{"line":1,"column":1}},"children":[{"type":"text","value":"Time-lapse Camera Applications","position":{"start":{"line":1,"column":1},"end":{"line":1,"column":1}},"key":"p8hxbUlNAV"}],"identifier":"time-lapse-camera-applications","label":"Time-lapse Camera Applications","html_id":"time-lapse-camera-applications","implicit":true,"key":"R70eDEpVwL"},{"type":"paragraph","position":{"start":{"line":3,"column":1},"end":{"line":3,"column":1}},"children":[{"type":"text","value":"Installing snow poles in front of time-lapse camera provides low-cost, long-term snow depth timeseries. Snow depths from the 2020 SnowEx time-lapse imagery have been manually processed with estimation of submission to the NSIDC database in summer 2021.","position":{"start":{"line":3,"column":1},"end":{"line":3,"column":1}},"key":"ofjwwl8Qlu"}],"key":"JNsGZvclgL"},{"type":"paragraph","position":{"start":{"line":5,"column":1},"end":{"line":5,"column":1}},"children":[{"type":"text","value":"The snow depth is the difference between the number of pixels in a snow-free image and an image with snow, with a conversion from pixels to centimeters (","position":{"start":{"line":5,"column":1},"end":{"line":5,"column":1}},"key":"geWGSOkJsZ"},{"type":"strong","position":{"start":{"line":5,"column":1},"end":{"line":5,"column":1}},"children":[{"type":"text","value":"Figure 1","position":{"start":{"line":5,"column":1},"end":{"line":5,"column":1}},"key":"zcIdUkMYLv"}],"key":"QCGNwBHM1z"},{"type":"text","value":").","position":{"start":{"line":5,"column":1},"end":{"line":5,"column":1}},"key":"CI1BglNaEQ"}],"key":"PSODXnCsYR"}],"key":"vHkNLRMMRm"},{"type":"block","kind":"notebook-content","children":[{"type":"image","url":"/snow-observations-cookbook/build/timelapse-camera-tut-91bd3e2199e99c14dac6864ae3ff5a29.png","alt":"equation","position":{"start":{"line":1,"column":1},"end":{"line":1,"column":1}},"key":"g7xksHsOBs","urlSource":"./images/time-lapse-camera/timelapse-camera-tutorial_27_0.png"},{"type":"paragraph","position":{"start":{"line":3,"column":1},"end":{"line":3,"column":1}},"children":[{"type":"strong","position":{"start":{"line":3,"column":1},"end":{"line":3,"column":1}},"children":[{"type":"text","value":"Figure 1: Equation to extract snow depth from camera images. For each image, take the difference in pixels between the length of a snow-free stake and the length of the stake and multiply by length(cm)/pixel. The ratio can be found by dividing the full length of the stake (304.8 cm) by the length of a snow-free stake in pixels.","position":{"start":{"line":3,"column":1},"end":{"line":3,"column":1}},"key":"HVIh4mfCH1"}],"key":"MENAVtOrC6"}],"key":"dH0YKiwmB2"},{"type":"paragraph","position":{"start":{"line":5,"column":1},"end":{"line":5,"column":1}},"children":[{"type":"text","value":"Snow depth can be obtained in this manner manually, but it is now easier to determine the pixel size of the stakes through machine learning. For the sake of completeness, we will provide a brief example using the camera imagery above. Otherwise, users interested in using the camera imagery with machine learning are encouraged to check out the following resources by Katherine Breen and others:","position":{"start":{"line":5,"column":1},"end":{"line":5,"column":1}},"key":"kWdU5K0wgd"}],"key":"BLpD8nOtOe"},{"type":"paragraph","position":{"start":{"line":7,"column":1},"end":{"line":8,"column":1}},"children":[{"type":"strong","position":{"start":{"line":7,"column":1},"end":{"line":7,"column":1}},"children":[{"type":"text","value":"Publication on method","position":{"start":{"line":7,"column":1},"end":{"line":7,"column":1}},"key":"xsfmHMKw5l"}],"key":"ZihhVlNXmt"},{"type":"break","position":{"start":{"line":7,"column":1},"end":{"line":7,"column":1}},"key":"yKBtLP0fmb"},{"type":"text","value":"Breen C. M., W. R. Currier, C. Vuyovich, et al. 2024. “Snow Depth Extraction From Time‐Lapse Imagery Using a Keypoint Deep Learning Model.” Water Resources Research 60 (7): [10.1029/2023wr036682]","position":{"start":{"line":7,"column":1},"end":{"line":7,"column":1}},"key":"ZalF57KdKZ"}],"key":"trjau57yQ4"},{"type":"paragraph","position":{"start":{"line":10,"column":1},"end":{"line":11,"column":1}},"children":[{"type":"strong","position":{"start":{"line":10,"column":1},"end":{"line":10,"column":1}},"children":[{"type":"text","value":"Github page for algorithm","position":{"start":{"line":10,"column":1},"end":{"line":10,"column":1}},"key":"y4OIhzw5sj"}],"key":"p4jVwju0C8"},{"type":"break","position":{"start":{"line":10,"column":1},"end":{"line":10,"column":1}},"key":"BpWL4dBDn2"},{"type":"link","url":"https://github.com/catherine-m-breen/snowpoles","position":{"start":{"line":10,"column":1},"end":{"line":10,"column":1}},"children":[{"type":"text","value":"https://​github​.com​/catherine​-m​-breen​/snowpoles","position":{"start":{"line":10,"column":1},"end":{"line":10,"column":1}},"key":"prU50DpjeF"}],"urlSource":"https://github.com/catherine-m-breen/snowpoles","error":true,"key":"bfwADgfuwI"}],"key":"p8m6oOsZx1"}],"key":"b1HxcnaIbj"},{"type":"block","kind":"notebook-content","children":[{"type":"paragraph","position":{"start":{"line":1,"column":1},"end":{"line":1,"column":1}},"children":[{"type":"text","value":"In the example images above, we use the red pole in the fully snow-off and snow-on images for estimation.","position":{"start":{"line":1,"column":1},"end":{"line":1,"column":1}},"key":"Xy4eBeyJ5I"}],"key":"ZV8xhuI9IZ"},{"type":"paragraph","position":{"start":{"line":3,"column":1},"end":{"line":3,"column":1}},"children":[{"type":"text","value":"For the snow-off image, the length of the red pole is ","position":{"start":{"line":3,"column":1},"end":{"line":3,"column":1}},"key":"txYJmW2hEh"},{"type":"strong","position":{"start":{"line":3,"column":1},"end":{"line":3,"column":1}},"children":[{"type":"text","value":"136 pixels","position":{"start":{"line":3,"column":1},"end":{"line":3,"column":1}},"key":"SifsuQ5iwZ"}],"key":"YknJjQRIvH"},{"type":"text","value":". If we assume that the pole is 304.8 cm in length, then each pixel is approximately ","position":{"start":{"line":3,"column":1},"end":{"line":3,"column":1}},"key":"i1oO8Ae6vI"},{"type":"strong","position":{"start":{"line":3,"column":1},"end":{"line":3,"column":1}},"children":[{"type":"text","value":"2.24 cm","position":{"start":{"line":3,"column":1},"end":{"line":3,"column":1}},"key":"dtlL5pCLAd"}],"key":"JjLODtuw9f"},{"type":"text","value":" in length.","position":{"start":{"line":3,"column":1},"end":{"line":3,"column":1}},"key":"bb0L90ordd"}],"key":"NJ3KFfTXz4"},{"type":"paragraph","position":{"start":{"line":5,"column":1},"end":{"line":5,"column":1}},"children":[{"type":"text","value":"For the snow-on image, the length of the red pole is ","position":{"start":{"line":5,"column":1},"end":{"line":5,"column":1}},"key":"EvOerh7vGW"},{"type":"strong","position":{"start":{"line":5,"column":1},"end":{"line":5,"column":1}},"children":[{"type":"text","value":"72 pixels","position":{"start":{"line":5,"column":1},"end":{"line":5,"column":1}},"key":"OylcbfqLR7"}],"key":"X5DYDdD05G"},{"type":"text","value":", much shorter than the snow-off length. So, there is a ","position":{"start":{"line":5,"column":1},"end":{"line":5,"column":1}},"key":"GTNF0kON8V"},{"type":"strong","position":{"start":{"line":5,"column":1},"end":{"line":5,"column":1}},"children":[{"type":"text","value":"~64 pixel","position":{"start":{"line":5,"column":1},"end":{"line":5,"column":1}},"key":"b2Grimo7uv"}],"key":"SDGuFpUuGj"},{"type":"text","value":" difference between the snow-on and snow-off lengths. Using the equation in Figure 1, we can calculate snow depth:","position":{"start":{"line":5,"column":1},"end":{"line":5,"column":1}},"key":"h2kPj2Upna"}],"key":"wgoZ3SAUTF"},{"type":"paragraph","position":{"start":{"line":7,"column":1},"end":{"line":7,"column":1}},"children":[{"type":"text","value":"Depth = 2.24 * (136-72) = ","position":{"start":{"line":7,"column":1},"end":{"line":7,"column":1}},"key":"RAx2SeHzJy"},{"type":"strong","position":{"start":{"line":7,"column":1},"end":{"line":7,"column":1}},"children":[{"type":"text","value":"143.36 cm","position":{"start":{"line":7,"column":1},"end":{"line":7,"column":1}},"key":"V0wMusRFGO"}],"key":"Ks5m0OI4cU"}],"key":"XMieHWXW7B"}],"key":"p6VIMj7GoB"},{"type":"block","kind":"notebook-content","children":[{"type":"paragraph","position":{"start":{"line":1,"column":1},"end":{"line":1,"column":1}},"children":[{"type":"emphasis","position":{"start":{"line":1,"column":1},"end":{"line":1,"column":1}},"children":[{"type":"text","value":"Acknowledgements: Anthony Arendt, Scott Henderson, Micah Johnson, Carrie Vuyovich, Ryan Currier, Megan Mason, Mark Raleigh","position":{"start":{"line":1,"column":1},"end":{"line":1,"column":1}},"key":"oLRXh3FXjg"}],"key":"q6fLewh3YS"}],"key":"WXaq4mJzqx"},{"type":"paragraph","position":{"start":{"line":3,"column":1},"end":{"line":4,"column":1}},"children":[{"type":"strong","position":{"start":{"line":3,"column":1},"end":{"line":3,"column":1}},"children":[{"type":"text","value":"Additional References","position":{"start":{"line":3,"column":1},"end":{"line":3,"column":1}},"key":"fFwMOuos8m"}],"key":"dG90hZ3a1z"},{"type":"break","position":{"start":{"line":3,"column":1},"end":{"line":3,"column":1}},"key":"kQFvioC7nT"},{"type":"text","value":"Dickerson-Lange et al., 2017. ","position":{"start":{"line":3,"column":1},"end":{"line":3,"column":1}},"key":"dSvDbx4cSS"},{"type":"emphasis","position":{"start":{"line":3,"column":1},"end":{"line":3,"column":1}},"children":[{"type":"text","value":"Snow disappearance timing is dominated by forest effects on snow accumulation in warm winter climates of the Pacific Northwest, United States.","position":{"start":{"line":3,"column":1},"end":{"line":3,"column":1}},"key":"auX9WXxJXo"}],"key":"SS2Z3br5Df"},{"type":"text","value":" Hydrological Processes. Vol 31, Issue 10. 13 February 2017. ","position":{"start":{"line":3,"column":1},"end":{"line":3,"column":1}},"key":"cS2OGcfmfk"},{"type":"cite","url":"https://doi.org/10.1002/hyp.11144","position":{"start":{"line":3,"column":1},"end":{"line":3,"column":1}},"children":[{"type":"text","value":"Dickerson‐Lange ","key":"J5jijYb3kl"},{"type":"emphasis","children":[{"type":"text","value":"et al.","key":"JrvKsnvcA6"}],"key":"BzWNxRLFge"},{"type":"text","value":" (2017)","key":"toCt42RFQy"}],"kind":"narrative","label":"Dickerson_Lange_2017","identifier":"https://doi.org/10.1002/hyp.11144","enumerator":"1","key":"oPKWbiHWUQ"}],"key":"m0iv9Jw2DT"},{"type":"paragraph","position":{"start":{"line":6,"column":1},"end":{"line":6,"column":1}},"children":[{"type":"text","value":"Raleigh et al., 2013. ","position":{"start":{"line":6,"column":1},"end":{"line":6,"column":1}},"key":"h3A2D3JxLD"},{"type":"emphasis","position":{"start":{"line":6,"column":1},"end":{"line":6,"column":1}},"children":[{"type":"text","value":"Approximating snow surface temperature from standard temperature and humidity data: New possibilities for snow model and remote sensing evaluation","position":{"start":{"line":6,"column":1},"end":{"line":6,"column":1}},"key":"Pfg6Y2za6n"}],"key":"k6spC92ADL"},{"type":"text","value":". Water Resources Research. Vol 49, Issue 12. 07 November 2013.  ","position":{"start":{"line":6,"column":1},"end":{"line":6,"column":1}},"key":"beswNxJxFT"},{"type":"cite","url":"https://doi.org/10.1002/2013WR013958","position":{"start":{"line":6,"column":1},"end":{"line":6,"column":1}},"children":[{"type":"text","value":"Raleigh ","key":"WtYBYj25z9"},{"type":"emphasis","children":[{"type":"text","value":"et al.","key":"Zop1gszv4k"}],"key":"PE5sdlvZ1M"},{"type":"text","value":" (2013)","key":"JxiWXbnfe4"}],"kind":"narrative","label":"Raleigh_2013","identifier":"https://doi.org/10.1002/2013WR013958","enumerator":"2","key":"YypvUt3Pf3"}],"key":"j4BxoUeP6G"}],"key":"M3VI22Wji1"}],"key":"F3j83qwr3Z"},"references":{"cite":{"order":["Dickerson_Lange_2017","Raleigh_2013"],"data":{"Dickerson_Lange_2017":{"label":"Dickerson_Lange_2017","enumerator":"1","doi":"10.1002/hyp.11144","html":"Dickerson‐Lange, S. E., Gersonde, R. F., Hubbart, J. A., Link, T. E., Nolin, A. W., Perry, G. H., Roth, T. R., Wayand, N. E., & Lundquist, J. D. (2017). Snow disappearance timing is dominated by forest effects on snow accumulation in warm winter climates of the Pacific Northwest, United States. <i>Hydrological Processes</i>, <i>31</i>(10), 1846–1862. <a target=\"_blank\" rel=\"noreferrer\" href=\"https://doi.org/10.1002/hyp.11144\">10.1002/hyp.11144</a>","url":"https://doi.org/10.1002/hyp.11144"},"Raleigh_2013":{"label":"Raleigh_2013","enumerator":"2","doi":"10.1002/2013wr013958","html":"Raleigh, M. S., Landry, C. C., Hayashi, M., Quinton, W. L., & Lundquist, J. D. (2013). Approximating snow surface temperature from standard temperature and humidity data: New possibilities for snow model and remote sensing evaluation: Snow Surface Temperature Approximation. <i>Water Resources Research</i>, <i>49</i>(12), 8053–8069. <a target=\"_blank\" rel=\"noreferrer\" href=\"https://doi.org/10.1002/2013wr013958\">10.1002/2013wr013958</a>","url":"https://doi.org/10.1002/2013wr013958"}}}},"footer":{"navigation":{"prev":{"title":"Thermal Infrared","url":"/notebooks/thermal-ir-tutorial","group":"Observations"},"next":{"title":"UAVSAR","url":"/notebooks/uavsar-tutorial","group":"Observations"}}},"domain":"http://localhost:3000"}